funckle/.cookiecutter/new-function/cookiecutter.json
funckle/.cookiecutter/new-function/{{ cookiecutter.project_slug }}/.funckle.json
funckle/.cookiecutter/new-function/{{ cookiecutter.project_slug }}/README.md
funckle/.cookiecutter/new-function/{{ cookiecutter.project_slug }}/main.py
funckle/.cookiecutter/new-function/{{ cookiecutter.project_slug }}/requirements.txt
funckle/__init__.py
funckle/cli/__init__.py
funckle/cli/deploy.py
funckle/cli/login.py
funckle/cli/settings.py
funckle/function/__init__.py
funckle/function/events/__init__.py
funckle/function/events/_base.py
funckle/function/events/access_request.py
funckle/function/events/branch.py
funckle/function/events/comment.py
funckle/function/events/commit.py
funckle/function/events/stream.py
funckle/function/handler.py
funckle/function/settings.py
funckle-0.1.4.dist-info/METADATA
funckle-0.1.4.dist-info/WHEEL
funckle-0.1.4.dist-info/entry_points.txt
funckle-0.1.4.dist-info/RECORD
