Metadata-Version: 2.1
Name: funckle
Version: 0.1.4
Summary: 
Author: antoinedao
Author-email: antoinedao1@gmail.com
Requires-Python: >=3.11,<4.0
Classifier: Programming Language :: Python :: 3
Classifier: Programming Language :: Python :: 3.11
Requires-Dist: click (>=8.1.7,<9.0.0)
Requires-Dist: cookiecutter (>=2.3.0,<3.0.0)
Requires-Dist: flask (>=2.3.2,<3.0.0)
Requires-Dist: functions-framework (>=3.0.0,<4.0.0)
Requires-Dist: gql[all] (>=3.4.1,<4.0.0)
Requires-Dist: pydantic-settings (>=2.0.3,<3.0.0)
Requires-Dist: requests (>=2.31.0,<3.0.0)
Requires-Dist: specklepy (>=2.16.0,<3.0.0)
Requires-Dist: typer[all] (>=0.9.0,<0.10.0)
